<?xml version='1.1' encoding='UTF-8'?>
<com.cloudbees.jenkins.support.filter.ContentMappings resolves-to="com.cloudbees.jenkins.support.filter.ContentMappings$XmlProxy" plugin="support-core@2.52">
  <stopWords>
    <string>authenticated</string>
    <string>freebsd</string>
    <string>admin</string>
    <string>mac</string>
    <string>unknown</string>
    <string>computer</string>
    <string>view</string>
    <string>linux</string>
    <string>debian</string>
    <string>jenkins</string>
    <string>win</string>
    <string>macos</string>
    <string>all</string>
    <string>macosx</string>
    <string>item</string>
    <string>everyone</string>
    <string>ubuntu</string>
    <string>label</string>
    <string>windows</string>
    <string>mac os x</string>
    <string>master</string>
    <string>node</string>
    <string>system</string>
    <string>fedora</string>
    <string>anonymous</string>
    <string>sunos</string>
    <string>user</string>
    <string>red hat</string>
  </stopWords>
  <mappings/>
</com.cloudbees.jenkins.support.filter.ContentMappings>